elementary_python_sdk/core/__init__.py
elementary_python_sdk/core/cloud/cloud_client.py
elementary_python_sdk/core/cloud/request.py
elementary_python_sdk/core/logger.py
elementary_python_sdk/core/py.typed
elementary_python_sdk/core/test_context.py
elementary_python_sdk/core/tests/__init__.py
elementary_python_sdk/core/tests/context.py
elementary_python_sdk/core/tests/runners/base.py
elementary_python_sdk/core/tests/runners/executor.py
elementary_python_sdk/core/tests/runners/impl/__init__.py
elementary_python_sdk/core/tests/runners/impl/boolean_test.py
elementary_python_sdk/core/tests/runners/impl/expected_range.py
elementary_python_sdk/core/tests/runners/impl/expected_values.py
elementary_python_sdk/core/tests/runners/impl/row_count.py
elementary_python_sdk/core/types/__init__.py
elementary_python_sdk/core/types/asset.py
elementary_python_sdk/core/types/base.py
elementary_python_sdk/core/types/task.py
elementary_python_sdk/core/types/test.py
elementary_python_sdk_core-0.2.0.dist-info/METADATA
elementary_python_sdk_core-0.2.0.dist-info/WHEEL
elementary_python_sdk_core-0.2.0.dist-info/RECORD
