Metadata-Version: 2.4
Name: elementary-python-sdk-core
Version: 0.2.0
Summary: Core runtime for Elementary's Python SDK (types, context, logger)
Author: Elementary Data
Author-email: team@elementary-data.com
Requires-Python: >=3.10
Classifier: Programming Language :: Python :: 3
Classifier: Programming Language :: Python :: 3.10
Classifier: Programming Language :: Python :: 3.11
Classifier: Programming Language :: Python :: 3.12
Classifier: Programming Language :: Python :: 3.13
Classifier: Programming Language :: Python :: 3.14
Requires-Dist: pydantic (>=2.10.0)
Requires-Dist: requests (>=2.28.1,<3.0.0)
